mosaik_components/emissions/__init__.py
mosaik_components/emissions/data/data.csv
mosaik_components/emissions/emission_simulator.py
mosaik_emissions-0.1.1.dist-info/AUTHORS.txt
mosaik_emissions-0.1.1.dist-info/LICENSE
mosaik_emissions-0.1.1.dist-info/METADATA
mosaik_emissions-0.1.1.dist-info/WHEEL
mosaik_emissions-0.1.1.dist-info/RECORD
