Metadata-Version: 2.1
Name: mosaik-emissions
Version: 0.1.1
Summary: Emissions simulator for Mosaik
License: LICENSE
Author: Danila Valko
Author-email: mosaik@offis.de
Requires-Python: >=3.9,<4.0
Classifier: License :: Other/Proprietary License
Classifier: Programming Language :: Python :: 3
Classifier: Programming Language :: Python :: 3.9
Classifier: Programming Language :: Python :: 3.10
Classifier: Programming Language :: Python :: 3.11
Classifier: Programming Language :: Python :: 3.12
Requires-Dist: arrow (>=1.3.0,<2.0.0)
Requires-Dist: mosaik (>=3.2.0,<4.0.0)
Requires-Dist: mosaik-api-v3 (>=3.0.7,<4.0.0)
Requires-Dist: numpy (>=1.26.1,<2.0.0)
Requires-Dist: pandas (>=2.1.2,<3.0.0)
Requires-Dist: tqdm (>=4.66.1,<5.0.0)
